chunk_http_tornado/__init__.py
chunk_http_tornado/client.py
chunk_http_tornado/handler.py
chunk_http_tornado-0.1.0.dist-info/AUTHORS
chunk_http_tornado-0.1.0.dist-info/METADATA
chunk_http_tornado-0.1.0.dist-info/WHEEL
chunk_http_tornado-0.1.0.dist-info/pbr.json
chunk_http_tornado-0.1.0.dist-info/top_level.txt
chunk_http_tornado-0.1.0.dist-info/RECORD
